uq4k/__init__.py
uq4k/blackbox/__init__.py
uq4k/blackbox/bb_optimizer.py
uq4k/gradient/__init__.py
uq4k/gradient/early_stopper.py
uq4k/gradient/gd_optimizer.py
uq4k/models/__init__.py
uq4k/models/base_model.py
uq4k/models/linear_model.py
uq4k/models/loss.py
uq4k/models/predprey_model.py
uq4k/models/quadratic_model.py
uq4k/plotting/__init__.py
uq4k/plotting/pred_prey.py
uq4k-0.1.0b3.dist-info/AUTHORS.rst
uq4k-0.1.0b3.dist-info/LICENSE
uq4k-0.1.0b3.dist-info/METADATA
uq4k-0.1.0b3.dist-info/WHEEL
uq4k-0.1.0b3.dist-info/top_level.txt
uq4k-0.1.0b3.dist-info/RECORD
