Metadata-Version: 2.1
Name: uq4k
Version: 0.1.0b3
Summary: UQ4k: Uncertaininty Quantification of the 4th Kind
Home-page: https://github.com/JPLMLIA/UQ4K
Author: Mahdy Shirdel
Author-email: mshirdel@utexas.edu
License: MIT license
Keywords: uq4k
Platform: UNKNOWN
Classifier: Development Status :: 4 - Beta
Classifier: Intended Audience :: Developers
Classifier: License :: OSI Approved :: MIT License
Classifier: Natural Language :: English
Classifier: Programming Language :: Python :: 3
Classifier: Programming Language :: Python :: 3.6
Classifier: Programming Language :: Python :: 3.7
Classifier: Programming Language :: Python :: 3.8
Requires-Python: >=3.6
License-File: LICENSE
License-File: AUTHORS.rst
Requires-Dist: cvxpy (==1.1.18)
Requires-Dist: miniball (==1.1.0)
Requires-Dist: optax (==0.1.1)
Requires-Dist: numpy (==1.22.2)
Requires-Dist: scipy (==1.8.0)
Provides-Extra: dev
Requires-Dist: ipykernel (==6.9.1) ; extra == 'dev'
Requires-Dist: matplotlib (==3.5.1) ; extra == 'dev'
Requires-Dist: flake8 (==3.7.8) ; extra == 'dev'
Requires-Dist: isort (==5.9.1) ; extra == 'dev'
Requires-Dist: black (==21.6b0) ; extra == 'dev'
Requires-Dist: pre-commit (==2.13.0) ; extra == 'dev'
Requires-Dist: twine (==1.14.0) ; extra == 'dev'
Requires-Dist: build ; extra == 'dev'
